[
   {
      "category":"Dungeons&amp;Dragons",
      "files":[
         {
            "title":"Initiative Tracker",
            "url":"/pages/initracker.html"
         },
         {
            "title":"Brand new Initiative Tracker app for Android!",
            "url":"https://betas.to/nAVNsT3p"
         },
         {
            "title":"Tyrax' Antechamber",
            "url":"/pages/TyraxAntechamber01.html"
         }
      ]
   },
   {
      "category":"Android",
      "files":[
         {
            "title":"Useful Android Links",
            "url":"/pages/android_dev.html"
         }
      ]
   }
]
